myhook/__init__.py
oaipmharvest/__init__.py
oaipmharvest/cli.py
oaipmharvest/commons.py
oaipmharvest/models.py
oaipmharvest/oaistuff.py
oaipmharvest/repositorytools.py
oaipmharvest/settings.py
oaipmharvest-0.0.7.dist-info/licenses/LICENSE
oaipmharvest-0.0.7.dist-info/METADATA
oaipmharvest-0.0.7.dist-info/WHEEL
oaipmharvest-0.0.7.dist-info/entry_points.txt
oaipmharvest-0.0.7.dist-info/top_level.txt
oaipmharvest-0.0.7.dist-info/RECORD
