Metadata-Version: 2.4
Name: oaipmharvest
Version: 0.0.7
Summary: Highly configurable oai-harvester based on sickle.
Author-email: "UB Frankfurt a. M." <ublabs@ub.uni-frankfurt.de>
License: MPL 2.0
Project-URL: Homepage, https://github.com/ubffm/oaipmharvest
Platform: linux
Classifier: Development Status :: 3 - Alpha
Classifier: Environment :: Console
Classifier: License :: OSI Approved :: Mozilla Public License 2.0 (MPL 2.0)
Classifier: Operating System :: POSIX :: Linux
Requires-Python: >=3.9
License-File: LICENSE
Requires-Dist: arrow==1.4.0
Requires-Dist: requests[socks]==2.32.5
Requires-Dist: Sickle==0.7.0
Requires-Dist: voluptuous==0.15.2
Requires-Dist: tomli==2.2.1; python_version < "3.11"
Dynamic: license-file
